[{"id":"5885598","title":"Arztpraxisnotiz","reads":10088},{"id":"4824796","title":"Lippen wie Chiara Ohoven","reads":7973},{"id":"3630584","title":"The Monthly \"Tragic Proof of a Missing 'Why?' Chromosome\" Price","reads":7867},{"id":"4657102","title":"But I have promises to keep...","reads":6641},{"id":"1022222314","title":"Twoday-Tipp #5 - Blog Export on steroids","reads":6576},{"id":"4918223","title":"Das SP3 \"Zugriff verweigert\" Problem","reads":5182},{"id":"1022598268","title":"Videotool 2","reads":4226},{"id":"11581760","title":"Tool-Tipp: Fences","reads":4197},{"id":"38759480","title":"Das sexy vs. spleenig Klassifikationsmodell","reads":4191},{"id":"3747837","title":"Wie begeht man(n) den Prostata-Tag?","reads":3836},{"id":"1022396398","title":"Twoday-Tipp #8 - Videos anzeigen","reads":3557},{"id":"5846580","title":"Sexy und unwiderstehlich","reads":3291},{"id":"6057462","title":"Wochenendpumps","reads":3287},{"id":"5669788","title":"Das verlorene Recht auf schwarze Strümpfe","reads":3216},{"id":"5185134","title":"The Falling Man","reads":3120},{"id":"444864287","title":"Tag des Monarchisten","reads":2878},{"id":"6270388","title":"Dominance and Submission","reads":2853},{"id":"4953644","title":"Baba Yaga und die Lawn Dogs","reads":2783},{"id":"4723005","title":"Simplifikation","reads":2661},{"id":"5861745","title":"Kaffeenutellabrot to go","reads":2519}]